<?xml version="1.0" encoding="us-ascii"?>
<MQSim_Results>
	<Host>
		<Host.IO_Flow>
				 <Name>Host.IO_Flow.Trace.traces/test.trace</Name>
				 <Request_Count>263100</Request_Count>
				 <Read_Request_Count>197891</Read_Request_Count>
				 <Write_Request_Count>65209</Write_Request_Count>
				 <IOPS>inf</IOPS>
				 <IOPS_Read>inf</IOPS_Read>
				 <IOPS_Write>inf</IOPS_Write>
				 <IOPS_Write_after_PRECOND>inf</IOPS_Write_after_PRECOND>
				 <IOPS_Write_after_GC>902755.289883</IOPS_Write_after_GC>
				 <Bytes_Transferred>0.000000</Bytes_Transferred>
				 <Bytes_Transferred_Read>0.000000</Bytes_Transferred_Read>
				 <Bytes_Transferred_Write>0.000000</Bytes_Transferred_Write>
				 <Bandwidth>-nan(ind)</Bandwidth>
				 <Bandwidth_Read>-nan(ind)</Bandwidth_Read>
				 <Bandwidth_Write>-nan(ind)</Bandwidth_Write>
				 <Device_Response_Time>0</Device_Response_Time>
				 <Min_Device_Response_Time>1271310319</Min_Device_Response_Time>
				 <Max_Device_Response_Time>0</Max_Device_Response_Time>
				 <End_to_End_Request_Delay>0</End_to_End_Request_Delay>
				 <Min_End_to_End_Request_Delay>1271310319</Min_End_to_End_Request_Delay>
				 <Max_End_to_End_Request_Delay>0</Max_End_to_End_Request_Delay>
		</Host.IO_Flow>
	</Host>
	<SSDDevice>
		<SSDDevice.HostInterface>
				 <Name>SSDDevice.HostInterface</Name>
			<SSDDevice.IO_Stream>
					 <Stream_ID>0</Stream_ID>
					 <Average_Read_Transaction_Turnaround_Time>166</Average_Read_Transaction_Turnaround_Time>
					 <Average_Read_Transaction_Execution_Time>45</Average_Read_Transaction_Execution_Time>
					 <Average_Read_Transaction_Transfer_Time>2</Average_Read_Transaction_Transfer_Time>
					 <Average_Read_Transaction_Waiting_Time>118</Average_Read_Transaction_Waiting_Time>
					 <Average_Write_Transaction_Turnaround_Time>18481</Average_Write_Transaction_Turnaround_Time>
					 <Average_Write_Transaction_Execution_Time>700</Average_Write_Transaction_Execution_Time>
					 <Average_Write_Transaction_Transfer_Time>2</Average_Write_Transaction_Transfer_Time>
					 <Average_Write_Transaction_Waiting_Time>17778</Average_Write_Transaction_Waiting_Time>
			</SSDDevice.IO_Stream>
		</SSDDevice.HostInterface>
		<SSDDevice.FTL Issued_Flash_Read_CMD="0" Issued_Flash_Interleaved_Read_CMD="0" Issued_Flash_Multiplane_Read_CMD="3182" Issued_Flash_Copyback_Read_CMD="0" Issued_Flash_Multiplane_Copyback_Read_CMD="0" Issued_Flash_Program_CMD="17" Issued_Flash_Interleaved_Program_CMD="0" Issued_Flash_Multiplane_Program_CMD="971" Issued_Flash_Interleaved_Multiplane_Program_CMD="0" Issued_Flash_Copyback_Program_CMD="0" Issued_Flash_Multiplane_Copyback_Program_CMD="0" Issued_Flash_Erase_CMD="0" Issued_Flash_Interleaved_Erase_CMD="0" Issued_Flash_Multiplane_Erase_CMD="0" Issued_Flash_Interleaved_Multiplane_Erase_CMD="0" Issued_Flash_Suspend_Program_CMD="0" Issued_Flash_Suspend_Erase_CMD="0" Issued_Flash_Read_CMD_For_Mapping="0" Issued_Flash_Program_CMD_For_Mapping="0" CMT_Hits="16612" CMT_Hits_For_Read="12728" CMT_Hits_For_Write="3884" CMT_Misses="0" CMT_Misses_For_Read="0" CMT_Misses_For_Write="0" Total_CMT_Queries="16612" Total_CMT_Queries_For_Reads="12728" Total_CMT_Queries_For_Writes="3884" Total_GC_Executions="0" Average_Page_Movement_For_GC="-nan(ind)" Total_WL_Executions="0" Average_Page_Movement_For_WL="-nan(ind)"/>
		<SSDDevice.GearUp Utilization="0.000000" Host_write="3884" Host_write_subpgs="3884" Physical_write="0" Physical_write_count_subpg="0" Relief_write="0" Relief_proportion="0.000000" Total_WAF="0.000000" Total_WAF_subpgs="0.000000" Additional_WAF_by_mapping="0" WAI WAF Max_consecutive_gc_write="0" Relief_type="0" Relief_ratio="-nan(ind)" Reliefed_Space Relief_Histogram>16384 Relief_freq="-nan(ind)" Relief_count="0" Erase_count="0"/>
		<SSDDevice.TSU>
			<SSDDevice.TSU.User_Read_TR_Queue Name="User_Read_TR_Queue@0@0" No_Of_Transactions_Enqueued="788" No_Of_Transactions_Dequeued="788" Avg_Queue_Length="1.275577" Max_Queue_Length="16" STDev_Queue_Length="4.993444" Avg_Transaction_Waiting_Time="116" Max_Transaction_Waiting_Time="700"/>
			<SSDDevice.TSU.User_Read_TR_Queue Name="User_Read_TR_Queue@0@1" No_Of_Transactions_Enqueued="788" No_Of_Transactions_Dequeued="788" Avg_Queue_Length="1.262302" Max_Queue_Length="16" STDev_Queue_Length="4.941739" Avg_Transaction_Waiting_Time="115" Max_Transaction_Waiting_Time="695"/>
			<SSDDevice.TSU.User_Read_TR_Queue Name="User_Read_TR_Queue@0@2" No_Of_Transactions_Enqueued="784" No_Of_Transactions_Dequeued="784" Avg_Queue_Length="1.261010" Max_Queue_Length="16" STDev_Queue_Length="4.936012" Avg_Transaction_Waiting_Time="116" Max_Transaction_Waiting_Time="699"/>
			<SSDDevice.TSU.User_Read_TR_Queue Name="User_Read_TR_Queue@0@3" No_Of_Transactions_Enqueued="788" No_Of_Transactions_Dequeued="788" Avg_Queue_Length="1.258982" Max_Queue_Length="16" STDev_Queue_Length="4.928286" Avg_Transaction_Waiting_Time="115" Max_Transaction_Waiting_Time="697"/>
			<SSDDevice.TSU.User_Read_TR_Queue Name="User_Read_TR_Queue@1@0" No_Of_Transactions_Enqueued="796" No_Of_Transactions_Dequeued="796" Avg_Queue_Length="1.307949" Max_Queue_Length="20" STDev_Queue_Length="5.748129" Avg_Transaction_Waiting_Time="118" Max_Transaction_Waiting_Time="700"/>
			<SSDDevice.TSU.User_Read_TR_Queue Name="User_Read_TR_Queue@1@1" No_Of_Transactions_Enqueued="800" No_Of_Transactions_Dequeued="800" Avg_Queue_Length="1.322840" Max_Queue_Length="24" STDev_Queue_Length="6.385617" Avg_Transaction_Waiting_Time="119" Max_Transaction_Waiting_Time="699"/>
			<SSDDevice.TSU.User_Read_TR_Queue Name="User_Read_TR_Queue@1@2" No_Of_Transactions_Enqueued="788" No_Of_Transactions_Dequeued="788" Avg_Queue_Length="1.257380" Max_Queue_Length="16" STDev_Queue_Length="4.922125" Avg_Transaction_Waiting_Time="115" Max_Transaction_Waiting_Time="700"/>
			<SSDDevice.TSU.User_Read_TR_Queue Name="User_Read_TR_Queue@1@3" No_Of_Transactions_Enqueued="804" No_Of_Transactions_Dequeued="804" Avg_Queue_Length="1.318025" Max_Queue_Length="28" STDev_Queue_Length="6.886367" Avg_Transaction_Waiting_Time="118" Max_Transaction_Waiting_Time="694"/>
			<SSDDevice.TSU.User_Read_TR_Queue Name="User_Read_TR_Queue@2@0" No_Of_Transactions_Enqueued="808" No_Of_Transactions_Dequeued="808" Avg_Queue_Length="1.363047" Max_Queue_Length="32" STDev_Queue_Length="7.623561" Avg_Transaction_Waiting_Time="121" Max_Transaction_Waiting_Time="694"/>
			<SSDDevice.TSU.User_Read_TR_Queue Name="User_Read_TR_Queue@2@1" No_Of_Transactions_Enqueued="792" No_Of_Transactions_Dequeued="792" Avg_Queue_Length="1.277892" Max_Queue_Length="16" STDev_Queue_Length="5.002698" Avg_Transaction_Waiting_Time="116" Max_Transaction_Waiting_Time="699"/>
			<SSDDevice.TSU.User_Read_TR_Queue Name="User_Read_TR_Queue@2@2" No_Of_Transactions_Enqueued="800" No_Of_Transactions_Dequeued="800" Avg_Queue_Length="1.307075" Max_Queue_Length="24" STDev_Queue_Length="6.309638" Avg_Transaction_Waiting_Time="118" Max_Transaction_Waiting_Time="694"/>
			<SSDDevice.TSU.User_Read_TR_Queue Name="User_Read_TR_Queue@2@3" No_Of_Transactions_Enqueued="808" No_Of_Transactions_Dequeued="808" Avg_Queue_Length="1.445764" Max_Queue_Length="32" STDev_Queue_Length="8.087652" Avg_Transaction_Waiting_Time="129" Max_Transaction_Waiting_Time="700"/>
			<SSDDevice.TSU.User_Read_TR_Queue Name="User_Read_TR_Queue@3@0" No_Of_Transactions_Enqueued="788" No_Of_Transactions_Dequeued="788" Avg_Queue_Length="1.276177" Max_Queue_Length="16" STDev_Queue_Length="4.995760" Avg_Transaction_Waiting_Time="116" Max_Transaction_Waiting_Time="700"/>
			<SSDDevice.TSU.User_Read_TR_Queue Name="User_Read_TR_Queue@3@1" No_Of_Transactions_Enqueued="796" No_Of_Transactions_Dequeued="796" Avg_Queue_Length="1.306824" Max_Queue_Length="20" STDev_Queue_Length="5.742772" Avg_Transaction_Waiting_Time="118" Max_Transaction_Waiting_Time="699"/>
			<SSDDevice.TSU.User_Read_TR_Queue Name="User_Read_TR_Queue@3@2" No_Of_Transactions_Enqueued="804" No_Of_Transactions_Dequeued="804" Avg_Queue_Length="1.322961" Max_Queue_Length="28" STDev_Queue_Length="6.912091" Avg_Transaction_Waiting_Time="118" Max_Transaction_Waiting_Time="694"/>
			<SSDDevice.TSU.User_Read_TR_Queue Name="User_Read_TR_Queue@3@3" No_Of_Transactions_Enqueued="796" No_Of_Transactions_Dequeued="796" Avg_Queue_Length="1.376627" Max_Queue_Length="20" STDev_Queue_Length="6.051165" Avg_Transaction_Waiting_Time="124" Max_Transaction_Waiting_Time="700"/>
			<SSDDevice.TSU.User_Write_TR_Queue Name="User_Write_TR_Queue@0@0" No_Of_Transactions_Enqueued="244" No_Of_Transactions_Dequeued="244" Avg_Queue_Length="60.328543" Max_Queue_Length="188" STDev_Queue_Length="825.041623" Avg_Transaction_Waiting_Time="17859" Max_Transaction_Waiting_Time="32979"/>
			<SSDDevice.TSU.User_Write_TR_Queue Name="User_Write_TR_Queue@0@1" No_Of_Transactions_Enqueued="244" No_Of_Transactions_Dequeued="244" Avg_Queue_Length="60.333225" Max_Queue_Length="188" STDev_Queue_Length="825.104331" Avg_Transaction_Waiting_Time="17860" Max_Transaction_Waiting_Time="32997"/>
			<SSDDevice.TSU.User_Write_TR_Queue Name="User_Write_TR_Queue@0@2" No_Of_Transactions_Enqueued="244" No_Of_Transactions_Dequeued="244" Avg_Queue_Length="60.329015" Max_Queue_Length="188" STDev_Queue_Length="825.048090" Avg_Transaction_Waiting_Time="17859" Max_Transaction_Waiting_Time="33020"/>
			<SSDDevice.TSU.User_Write_TR_Queue Name="User_Write_TR_Queue@0@3" No_Of_Transactions_Enqueued="240" No_Of_Transactions_Dequeued="240" Avg_Queue_Length="58.947167" Max_Queue_Length="188" STDev_Queue_Length="806.151812" Avg_Transaction_Waiting_Time="17741" Max_Transaction_Waiting_Time="32586"/>
			<SSDDevice.TSU.User_Write_TR_Queue Name="User_Write_TR_Queue@1@0" No_Of_Transactions_Enqueued="244" No_Of_Transactions_Dequeued="244" Avg_Queue_Length="60.323321" Max_Queue_Length="188" STDev_Queue_Length="824.969125" Avg_Transaction_Waiting_Time="17858" Max_Transaction_Waiting_Time="32981"/>
			<SSDDevice.TSU.User_Write_TR_Queue Name="User_Write_TR_Queue@1@1" No_Of_Transactions_Enqueued="244" No_Of_Transactions_Dequeued="244" Avg_Queue_Length="60.311695" Max_Queue_Length="188" STDev_Queue_Length="824.808729" Avg_Transaction_Waiting_Time="17854" Max_Transaction_Waiting_Time="32994"/>
			<SSDDevice.TSU.User_Write_TR_Queue Name="User_Write_TR_Queue@1@2" No_Of_Transactions_Enqueued="241" No_Of_Transactions_Dequeued="241" Avg_Queue_Length="58.986400" Max_Queue_Length="189" STDev_Queue_Length="808.820647" Avg_Transaction_Waiting_Time="17679" Max_Transaction_Waiting_Time="33032"/>
			<SSDDevice.TSU.User_Write_TR_Queue Name="User_Write_TR_Queue@1@3" No_Of_Transactions_Enqueued="240" No_Of_Transactions_Dequeued="240" Avg_Queue_Length="58.917513" Max_Queue_Length="188" STDev_Queue_Length="805.746018" Avg_Transaction_Waiting_Time="17732" Max_Transaction_Waiting_Time="32588"/>
			<SSDDevice.TSU.User_Write_TR_Queue Name="User_Write_TR_Queue@2@0" No_Of_Transactions_Enqueued="244" No_Of_Transactions_Dequeued="244" Avg_Queue_Length="60.352779" Max_Queue_Length="188" STDev_Queue_Length="825.372295" Avg_Transaction_Waiting_Time="17866" Max_Transaction_Waiting_Time="32998"/>
			<SSDDevice.TSU.User_Write_TR_Queue Name="User_Write_TR_Queue@2@1" No_Of_Transactions_Enqueued="244" No_Of_Transactions_Dequeued="244" Avg_Queue_Length="60.286435" Max_Queue_Length="188" STDev_Queue_Length="824.464569" Avg_Transaction_Waiting_Time="17847" Max_Transaction_Waiting_Time="32995"/>
			<SSDDevice.TSU.User_Write_TR_Queue Name="User_Write_TR_Queue@2@2" No_Of_Transactions_Enqueued="240" No_Of_Transactions_Dequeued="240" Avg_Queue_Length="58.920424" Max_Queue_Length="188" STDev_Queue_Length="805.786647" Avg_Transaction_Waiting_Time="17733" Max_Transaction_Waiting_Time="32566"/>
			<SSDDevice.TSU.User_Write_TR_Queue Name="User_Write_TR_Queue@2@3" No_Of_Transactions_Enqueued="243" No_Of_Transactions_Dequeued="243" Avg_Queue_Length="58.838694" Max_Queue_Length="187" STDev_Queue_Length="802.513345" Avg_Transaction_Waiting_Time="17490" Max_Transaction_Waiting_Time="32755"/>
			<SSDDevice.TSU.User_Write_TR_Queue Name="User_Write_TR_Queue@3@0" No_Of_Transactions_Enqueued="244" No_Of_Transactions_Dequeued="244" Avg_Queue_Length="60.330946" Max_Queue_Length="188" STDev_Queue_Length="825.073307" Avg_Transaction_Waiting_Time="17860" Max_Transaction_Waiting_Time="32994"/>
			<SSDDevice.TSU.User_Write_TR_Queue Name="User_Write_TR_Queue@3@1" No_Of_Transactions_Enqueued="244" No_Of_Transactions_Dequeued="244" Avg_Queue_Length="60.327963" Max_Queue_Length="188" STDev_Queue_Length="825.033809" Avg_Transaction_Waiting_Time="17859" Max_Transaction_Waiting_Time="33019"/>
			<SSDDevice.TSU.User_Write_TR_Queue Name="User_Write_TR_Queue@3@2" No_Of_Transactions_Enqueued="240" No_Of_Transactions_Dequeued="240" Avg_Queue_Length="58.925430" Max_Queue_Length="188" STDev_Queue_Length="805.854849" Avg_Transaction_Waiting_Time="17734" Max_Transaction_Waiting_Time="32576"/>
			<SSDDevice.TSU.User_Write_TR_Queue Name="User_Write_TR_Queue@3@3" No_Of_Transactions_Enqueued="244" No_Of_Transactions_Dequeued="244" Avg_Queue_Length="59.516613" Max_Queue_Length="188" STDev_Queue_Length="813.937225" Avg_Transaction_Waiting_Time="17619" Max_Transaction_Waiting_Time="32755"/>
			<SSDDevice.TSU.Mapping_Read_TR_Queue Name="Mapping_Read_TR_Queue@0@0" No_Of_Transactions_Enqueued="0" No_Of_Transactions_Dequeued="0" Avg_Queue_Length="0.000000" Max_Queue_Length="0" STDev_Queue_Length="0.000000" Avg_Transaction_Waiting_Time="9223372036854775808" Max_Transaction_Waiting_Time="0"/>
			<SSDDevice.TSU.Mapping_Read_TR_Queue Name="Mapping_Read_TR_Queue@0@1" No_Of_Transactions_Enqueued="0" No_Of_Transactions_Dequeued="0" Avg_Queue_Length="0.000000" Max_Queue_Length="0" STDev_Queue_Length="0.000000" Avg_Transaction_Waiting_Time="9223372036854775808" Max_Transaction_Waiting_Time="0"/>
			<SSDDevice.TSU.Mapping_Read_TR_Queue Name="Mapping_Read_TR_Queue@0@2" No_Of_Transactions_Enqueued="0" No_Of_Transactions_Dequeued="0" Avg_Queue_Length="0.000000" Max_Queue_Length="0" STDev_Queue_Length="0.000000" Avg_Transaction_Waiting_Time="9223372036854775808" Max_Transaction_Waiting_Time="0"/>
			<SSDDevice.TSU.Mapping_Read_TR_Queue Name="Mapping_Read_TR_Queue@0@3" No_Of_Transactions_Enqueued="0" No_Of_Transactions_Dequeued="0" Avg_Queue_Length="0.000000" Max_Queue_Length="0" STDev_Queue_Length="0.000000" Avg_Transaction_Waiting_Time="9223372036854775808" Max_Transaction_Waiting_Time="0"/>
			<SSDDevice.TSU.Mapping_Read_TR_Queue Name="Mapping_Read_TR_Queue@1@0" No_Of_Transactions_Enqueued="0" No_Of_Transactions_Dequeued="0" Avg_Queue_Length="0.000000" Max_Queue_Length="0" STDev_Queue_Length="0.000000" Avg_Transaction_Waiting_Time="9223372036854775808" Max_Transaction_Waiting_Time="0"/>
			<SSDDevice.TSU.Mapping_Read_TR_Queue Name="Mapping_Read_TR_Queue@1@1" No_Of_Transactions_Enqueued="0" No_Of_Transactions_Dequeued="0" Avg_Queue_Length="0.000000" Max_Queue_Length="0" STDev_Queue_Length="0.000000" Avg_Transaction_Waiting_Time="9223372036854775808" Max_Transaction_Waiting_Time="0"/>
			<SSDDevice.TSU.Mapping_Read_TR_Queue Name="Mapping_Read_TR_Queue@1@2" No_Of_Transactions_Enqueued="0" No_Of_Transactions_Dequeued="0" Avg_Queue_Length="0.000000" Max_Queue_Length="0" STDev_Queue_Length="0.000000" Avg_Transaction_Waiting_Time="9223372036854775808" Max_Transaction_Waiting_Time="0"/>
			<SSDDevice.TSU.Mapping_Read_TR_Queue Name="Mapping_Read_TR_Queue@1@3" No_Of_Transactions_Enqueued="0" No_Of_Transactions_Dequeued="0" Avg_Queue_Length="0.000000" Max_Queue_Length="0" STDev_Queue_Length="0.000000" Avg_Transaction_Waiting_Time="9223372036854775808" Max_Transaction_Waiting_Time="0"/>
			<SSDDevice.TSU.Mapping_Read_TR_Queue Name="Mapping_Read_TR_Queue@2@0" No_Of_Transactions_Enqueued="0" No_Of_Transactions_Dequeued="0" Avg_Queue_Length="0.000000" Max_Queue_Length="0" STDev_Queue_Length="0.000000" Avg_Transaction_Waiting_Time="9223372036854775808" Max_Transaction_Waiting_Time="0"/>
			<SSDDevice.TSU.Mapping_Read_TR_Queue Name="Mapping_Read_TR_Queue@2@1" No_Of_Transactions_Enqueued="0" No_Of_Transactions_Dequeued="0" Avg_Queue_Length="0.000000" Max_Queue_Length="0" STDev_Queue_Length="0.000000" Avg_Transaction_Waiting_Time="9223372036854775808" Max_Transaction_Waiting_Time="0"/>
			<SSDDevice.TSU.Mapping_Read_TR_Queue Name="Mapping_Read_TR_Queue@2@2" No_Of_Transactions_Enqueued="0" No_Of_Transactions_Dequeued="0" Avg_Queue_Length="0.000000" Max_Queue_Length="0" STDev_Queue_Length="0.000000" Avg_Transaction_Waiting_Time="9223372036854775808" Max_Transaction_Waiting_Time="0"/>
			<SSDDevice.TSU.Mapping_Read_TR_Queue Name="Mapping_Read_TR_Queue@2@3" No_Of_Transactions_Enqueued="0" No_Of_Transactions_Dequeued="0" Avg_Queue_Length="0.000000" Max_Queue_Length="0" STDev_Queue_Length="0.000000" Avg_Transaction_Waiting_Time="9223372036854775808" Max_Transaction_Waiting_Time="0"/>
			<SSDDevice.TSU.Mapping_Read_TR_Queue Name="Mapping_Read_TR_Queue@3@0" No_Of_Transactions_Enqueued="0" No_Of_Transactions_Dequeued="0" Avg_Queue_Length="0.000000" Max_Queue_Length="0" STDev_Queue_Length="0.000000" Avg_Transaction_Waiting_Time="9223372036854775808" Max_Transaction_Waiting_Time="0"/>
			<SSDDevice.TSU.Mapping_Read_TR_Queue Name="Mapping_Read_TR_Queue@3@1" No_Of_Transactions_Enqueued="0" No_Of_Transactions_Dequeued="0" Avg_Queue_Length="0.000000" Max_Queue_Length="0" STDev_Queue_Length="0.000000" Avg_Transaction_Waiting_Time="9223372036854775808" Max_Transaction_Waiting_Time="0"/>
			<SSDDevice.TSU.Mapping_Read_TR_Queue Name="Mapping_Read_TR_Queue@3@2" No_Of_Transactions_Enqueued="0" No_Of_Transactions_Dequeued="0" Avg_Queue_Length="0.000000" Max_Queue_Length="0" STDev_Queue_Length="0.000000" Avg_Transaction_Waiting_Time="9223372036854775808" Max_Transaction_Waiting_Time="0"/>
			<SSDDevice.TSU.Mapping_Read_TR_Queue Name="Mapping_Read_TR_Queue@3@3" No_Of_Transactions_Enqueued="0" No_Of_Transactions_Dequeued="0" Avg_Queue_Length="0.000000" Max_Queue_Length="0" STDev_Queue_Length="0.000000" Avg_Transaction_Waiting_Time="9223372036854775808" Max_Transaction_Waiting_Time="0"/>
			<SSDDevice.TSU.Mapping_Write_TR_Queue Name="Mapping_Write_TR_Queue@0@0" No_Of_Transactions_Enqueued="0" No_Of_Transactions_Dequeued="0" Avg_Queue_Length="0.000000" Max_Queue_Length="0" STDev_Queue_Length="0.000000" Avg_Transaction_Waiting_Time="9223372036854775808" Max_Transaction_Waiting_Time="0"/>
			<SSDDevice.TSU.Mapping_Write_TR_Queue Name="Mapping_Write_TR_Queue@0@1" No_Of_Transactions_Enqueued="0" No_Of_Transactions_Dequeued="0" Avg_Queue_Length="0.000000" Max_Queue_Length="0" STDev_Queue_Length="0.000000" Avg_Transaction_Waiting_Time="9223372036854775808" Max_Transaction_Waiting_Time="0"/>
			<SSDDevice.TSU.Mapping_Write_TR_Queue Name="Mapping_Write_TR_Queue@0@2" No_Of_Transactions_Enqueued="0" No_Of_Transactions_Dequeued="0" Avg_Queue_Length="0.000000" Max_Queue_Length="0" STDev_Queue_Length="0.000000" Avg_Transaction_Waiting_Time="9223372036854775808" Max_Transaction_Waiting_Time="0"/>
			<SSDDevice.TSU.Mapping_Write_TR_Queue Name="Mapping_Write_TR_Queue@0@3" No_Of_Transactions_Enqueued="0" No_Of_Transactions_Dequeued="0" Avg_Queue_Length="0.000000" Max_Queue_Length="0" STDev_Queue_Length="0.000000" Avg_Transaction_Waiting_Time="9223372036854775808" Max_Transaction_Waiting_Time="0"/>
			<SSDDevice.TSU.Mapping_Write_TR_Queue Name="Mapping_Write_TR_Queue@1@0" No_Of_Transactions_Enqueued="0" No_Of_Transactions_Dequeued="0" Avg_Queue_Length="0.000000" Max_Queue_Length="0" STDev_Queue_Length="0.000000" Avg_Transaction_Waiting_Time="9223372036854775808" Max_Transaction_Waiting_Time="0"/>
			<SSDDevice.TSU.Mapping_Write_TR_Queue Name="Mapping_Write_TR_Queue@1@1" No_Of_Transactions_Enqueued="0" No_Of_Transactions_Dequeued="0" Avg_Queue_Length="0.000000" Max_Queue_Length="0" STDev_Queue_Length="0.000000" Avg_Transaction_Waiting_Time="9223372036854775808" Max_Transaction_Waiting_Time="0"/>
			<SSDDevice.TSU.Mapping_Write_TR_Queue Name="Mapping_Write_TR_Queue@1@2" No_Of_Transactions_Enqueued="0" No_Of_Transactions_Dequeued="0" Avg_Queue_Length="0.000000" Max_Queue_Length="0" STDev_Queue_Length="0.000000" Avg_Transaction_Waiting_Time="9223372036854775808" Max_Transaction_Waiting_Time="0"/>
			<SSDDevice.TSU.Mapping_Write_TR_Queue Name="Mapping_Write_TR_Queue@1@3" No_Of_Transactions_Enqueued="0" No_Of_Transactions_Dequeued="0" Avg_Queue_Length="0.000000" Max_Queue_Length="0" STDev_Queue_Length="0.000000" Avg_Transaction_Waiting_Time="9223372036854775808" Max_Transaction_Waiting_Time="0"/>
			<SSDDevice.TSU.Mapping_Write_TR_Queue Name="Mapping_Write_TR_Queue@2@0" No_Of_Transactions_Enqueued="0" No_Of_Transactions_Dequeued="0" Avg_Queue_Length="0.000000" Max_Queue_Length="0" STDev_Queue_Length="0.000000" Avg_Transaction_Waiting_Time="9223372036854775808" Max_Transaction_Waiting_Time="0"/>
			<SSDDevice.TSU.Mapping_Write_TR_Queue Name="Mapping_Write_TR_Queue@2@1" No_Of_Transactions_Enqueued="0" No_Of_Transactions_Dequeued="0" Avg_Queue_Length="0.000000" Max_Queue_Length="0" STDev_Queue_Length="0.000000" Avg_Transaction_Waiting_Time="9223372036854775808" Max_Transaction_Waiting_Time="0"/>
			<SSDDevice.TSU.Mapping_Write_TR_Queue Name="Mapping_Write_TR_Queue@2@2" No_Of_Transactions_Enqueued="0" No_Of_Transactions_Dequeued="0" Avg_Queue_Length="0.000000" Max_Queue_Length="0" STDev_Queue_Length="0.000000" Avg_Transaction_Waiting_Time="9223372036854775808" Max_Transaction_Waiting_Time="0"/>
			<SSDDevice.TSU.Mapping_Write_TR_Queue Name="Mapping_Write_TR_Queue@2@3" No_Of_Transactions_Enqueued="0" No_Of_Transactions_Dequeued="0" Avg_Queue_Length="0.000000" Max_Queue_Length="0" STDev_Queue_Length="0.000000" Avg_Transaction_Waiting_Time="9223372036854775808" Max_Transaction_Waiting_Time="0"/>
			<SSDDevice.TSU.Mapping_Write_TR_Queue Name="Mapping_Write_TR_Queue@3@0" No_Of_Transactions_Enqueued="0" No_Of_Transactions_Dequeued="0" Avg_Queue_Length="0.000000" Max_Queue_Length="0" STDev_Queue_Length="0.000000" Avg_Transaction_Waiting_Time="9223372036854775808" Max_Transaction_Waiting_Time="0"/>
			<SSDDevice.TSU.Mapping_Write_TR_Queue Name="Mapping_Write_TR_Queue@3@1" No_Of_Transactions_Enqueued="0" No_Of_Transactions_Dequeued="0" Avg_Queue_Length="0.000000" Max_Queue_Length="0" STDev_Queue_Length="0.000000" Avg_Transaction_Waiting_Time="9223372036854775808" Max_Transaction_Waiting_Time="0"/>
			<SSDDevice.TSU.Mapping_Write_TR_Queue Name="Mapping_Write_TR_Queue@3@2" No_Of_Transactions_Enqueued="0" No_Of_Transactions_Dequeued="0" Avg_Queue_Length="0.000000" Max_Queue_Length="0" STDev_Queue_Length="0.000000" Avg_Transaction_Waiting_Time="9223372036854775808" Max_Transaction_Waiting_Time="0"/>
			<SSDDevice.TSU.Mapping_Write_TR_Queue Name="Mapping_Write_TR_Queue@3@3" No_Of_Transactions_Enqueued="0" No_Of_Transactions_Dequeued="0" Avg_Queue_Length="0.000000" Max_Queue_Length="0" STDev_Queue_Length="0.000000" Avg_Transaction_Waiting_Time="9223372036854775808" Max_Transaction_Waiting_Time="0"/>
			<SSDDevice.TSU.GC_Read_TR_Queue Name="GC_Read_TR_Queue@0@0" No_Of_Transactions_Enqueued="0" No_Of_Transactions_Dequeued="0" Avg_Queue_Length="0.000000" Max_Queue_Length="0" STDev_Queue_Length="0.000000" Avg_Transaction_Waiting_Time="9223372036854775808" Max_Transaction_Waiting_Time="0"/>
			<SSDDevice.TSU.GC_Read_TR_Queue Name="GC_Read_TR_Queue@0@1" No_Of_Transactions_Enqueued="0" No_Of_Transactions_Dequeued="0" Avg_Queue_Length="0.000000" Max_Queue_Length="0" STDev_Queue_Length="0.000000" Avg_Transaction_Waiting_Time="9223372036854775808" Max_Transaction_Waiting_Time="0"/>
			<SSDDevice.TSU.GC_Read_TR_Queue Name="GC_Read_TR_Queue@0@2" No_Of_Transactions_Enqueued="0" No_Of_Transactions_Dequeued="0" Avg_Queue_Length="0.000000" Max_Queue_Length="0" STDev_Queue_Length="0.000000" Avg_Transaction_Waiting_Time="9223372036854775808" Max_Transaction_Waiting_Time="0"/>
			<SSDDevice.TSU.GC_Read_TR_Queue Name="GC_Read_TR_Queue@0@3" No_Of_Transactions_Enqueued="0" No_Of_Transactions_Dequeued="0" Avg_Queue_Length="0.000000" Max_Queue_Length="0" STDev_Queue_Length="0.000000" Avg_Transaction_Waiting_Time="9223372036854775808" Max_Transaction_Waiting_Time="0"/>
			<SSDDevice.TSU.GC_Read_TR_Queue Name="GC_Read_TR_Queue@1@0" No_Of_Transactions_Enqueued="0" No_Of_Transactions_Dequeued="0" Avg_Queue_Length="0.000000" Max_Queue_Length="0" STDev_Queue_Length="0.000000" Avg_Transaction_Waiting_Time="9223372036854775808" Max_Transaction_Waiting_Time="0"/>
			<SSDDevice.TSU.GC_Read_TR_Queue Name="GC_Read_TR_Queue@1@1" No_Of_Transactions_Enqueued="0" No_Of_Transactions_Dequeued="0" Avg_Queue_Length="0.000000" Max_Queue_Length="0" STDev_Queue_Length="0.000000" Avg_Transaction_Waiting_Time="9223372036854775808" Max_Transaction_Waiting_Time="0"/>
			<SSDDevice.TSU.GC_Read_TR_Queue Name="GC_Read_TR_Queue@1@2" No_Of_Transactions_Enqueued="0" No_Of_Transactions_Dequeued="0" Avg_Queue_Length="0.000000" Max_Queue_Length="0" STDev_Queue_Length="0.000000" Avg_Transaction_Waiting_Time="9223372036854775808" Max_Transaction_Waiting_Time="0"/>
			<SSDDevice.TSU.GC_Read_TR_Queue Name="GC_Read_TR_Queue@1@3" No_Of_Transactions_Enqueued="0" No_Of_Transactions_Dequeued="0" Avg_Queue_Length="0.000000" Max_Queue_Length="0" STDev_Queue_Length="0.000000" Avg_Transaction_Waiting_Time="9223372036854775808" Max_Transaction_Waiting_Time="0"/>
			<SSDDevice.TSU.GC_Read_TR_Queue Name="GC_Read_TR_Queue@2@0" No_Of_Transactions_Enqueued="0" No_Of_Transactions_Dequeued="0" Avg_Queue_Length="0.000000" Max_Queue_Length="0" STDev_Queue_Length="0.000000" Avg_Transaction_Waiting_Time="9223372036854775808" Max_Transaction_Waiting_Time="0"/>
			<SSDDevice.TSU.GC_Read_TR_Queue Name="GC_Read_TR_Queue@2@1" No_Of_Transactions_Enqueued="0" No_Of_Transactions_Dequeued="0" Avg_Queue_Length="0.000000" Max_Queue_Length="0" STDev_Queue_Length="0.000000" Avg_Transaction_Waiting_Time="9223372036854775808" Max_Transaction_Waiting_Time="0"/>
			<SSDDevice.TSU.GC_Read_TR_Queue Name="GC_Read_TR_Queue@2@2" No_Of_Transactions_Enqueued="0" No_Of_Transactions_Dequeued="0" Avg_Queue_Length="0.000000" Max_Queue_Length="0" STDev_Queue_Length="0.000000" Avg_Transaction_Waiting_Time="9223372036854775808" Max_Transaction_Waiting_Time="0"/>
			<SSDDevice.TSU.GC_Read_TR_Queue Name="GC_Read_TR_Queue@2@3" No_Of_Transactions_Enqueued="0" No_Of_Transactions_Dequeued="0" Avg_Queue_Length="0.000000" Max_Queue_Length="0" STDev_Queue_Length="0.000000" Avg_Transaction_Waiting_Time="9223372036854775808" Max_Transaction_Waiting_Time="0"/>
			<SSDDevice.TSU.GC_Read_TR_Queue Name="GC_Read_TR_Queue@3@0" No_Of_Transactions_Enqueued="0" No_Of_Transactions_Dequeued="0" Avg_Queue_Length="0.000000" Max_Queue_Length="0" STDev_Queue_Length="0.000000" Avg_Transaction_Waiting_Time="9223372036854775808" Max_Transaction_Waiting_Time="0"/>
			<SSDDevice.TSU.GC_Read_TR_Queue Name="GC_Read_TR_Queue@3@1" No_Of_Transactions_Enqueued="0" No_Of_Transactions_Dequeued="0" Avg_Queue_Length="0.000000" Max_Queue_Length="0" STDev_Queue_Length="0.000000" Avg_Transaction_Waiting_Time="9223372036854775808" Max_Transaction_Waiting_Time="0"/>
			<SSDDevice.TSU.GC_Read_TR_Queue Name="GC_Read_TR_Queue@3@2" No_Of_Transactions_Enqueued="0" No_Of_Transactions_Dequeued="0" Avg_Queue_Length="0.000000" Max_Queue_Length="0" STDev_Queue_Length="0.000000" Avg_Transaction_Waiting_Time="9223372036854775808" Max_Transaction_Waiting_Time="0"/>
			<SSDDevice.TSU.GC_Read_TR_Queue Name="GC_Read_TR_Queue@3@3" No_Of_Transactions_Enqueued="0" No_Of_Transactions_Dequeued="0" Avg_Queue_Length="0.000000" Max_Queue_Length="0" STDev_Queue_Length="0.000000" Avg_Transaction_Waiting_Time="9223372036854775808" Max_Transaction_Waiting_Time="0"/>
			<SSDDevice.TSU.GC_Write_TR_Queue Name="GC_Write_TR_Queue@0@0" No_Of_Transactions_Enqueued="0" No_Of_Transactions_Dequeued="0" Avg_Queue_Length="0.000000" Max_Queue_Length="0" STDev_Queue_Length="0.000000" Avg_Transaction_Waiting_Time="9223372036854775808" Max_Transaction_Waiting_Time="0"/>
			<SSDDevice.TSU.GC_Write_TR_Queue Name="GC_Write_TR_Queue@0@1" No_Of_Transactions_Enqueued="0" No_Of_Transactions_Dequeued="0" Avg_Queue_Length="0.000000" Max_Queue_Length="0" STDev_Queue_Length="0.000000" Avg_Transaction_Waiting_Time="9223372036854775808" Max_Transaction_Waiting_Time="0"/>
			<SSDDevice.TSU.GC_Write_TR_Queue Name="GC_Write_TR_Queue@0@2" No_Of_Transactions_Enqueued="0" No_Of_Transactions_Dequeued="0" Avg_Queue_Length="0.000000" Max_Queue_Length="0" STDev_Queue_Length="0.000000" Avg_Transaction_Waiting_Time="9223372036854775808" Max_Transaction_Waiting_Time="0"/>
			<SSDDevice.TSU.GC_Write_TR_Queue Name="GC_Write_TR_Queue@0@3" No_Of_Transactions_Enqueued="0" No_Of_Transactions_Dequeued="0" Avg_Queue_Length="0.000000" Max_Queue_Length="0" STDev_Queue_Length="0.000000" Avg_Transaction_Waiting_Time="9223372036854775808" Max_Transaction_Waiting_Time="0"/>
			<SSDDevice.TSU.GC_Write_TR_Queue Name="GC_Write_TR_Queue@1@0" No_Of_Transactions_Enqueued="0" No_Of_Transactions_Dequeued="0" Avg_Queue_Length="0.000000" Max_Queue_Length="0" STDev_Queue_Length="0.000000" Avg_Transaction_Waiting_Time="9223372036854775808" Max_Transaction_Waiting_Time="0"/>
			<SSDDevice.TSU.GC_Write_TR_Queue Name="GC_Write_TR_Queue@1@1" No_Of_Transactions_Enqueued="0" No_Of_Transactions_Dequeued="0" Avg_Queue_Length="0.000000" Max_Queue_Length="0" STDev_Queue_Length="0.000000" Avg_Transaction_Waiting_Time="9223372036854775808" Max_Transaction_Waiting_Time="0"/>
			<SSDDevice.TSU.GC_Write_TR_Queue Name="GC_Write_TR_Queue@1@2" No_Of_Transactions_Enqueued="0" No_Of_Transactions_Dequeued="0" Avg_Queue_Length="0.000000" Max_Queue_Length="0" STDev_Queue_Length="0.000000" Avg_Transaction_Waiting_Time="9223372036854775808" Max_Transaction_Waiting_Time="0"/>
			<SSDDevice.TSU.GC_Write_TR_Queue Name="GC_Write_TR_Queue@1@3" No_Of_Transactions_Enqueued="0" No_Of_Transactions_Dequeued="0" Avg_Queue_Length="0.000000" Max_Queue_Length="0" STDev_Queue_Length="0.000000" Avg_Transaction_Waiting_Time="9223372036854775808" Max_Transaction_Waiting_Time="0"/>
			<SSDDevice.TSU.GC_Write_TR_Queue Name="GC_Write_TR_Queue@2@0" No_Of_Transactions_Enqueued="0" No_Of_Transactions_Dequeued="0" Avg_Queue_Length="0.000000" Max_Queue_Length="0" STDev_Queue_Length="0.000000" Avg_Transaction_Waiting_Time="9223372036854775808" Max_Transaction_Waiting_Time="0"/>
			<SSDDevice.TSU.GC_Write_TR_Queue Name="GC_Write_TR_Queue@2@1" No_Of_Transactions_Enqueued="0" No_Of_Transactions_Dequeued="0" Avg_Queue_Length="0.000000" Max_Queue_Length="0" STDev_Queue_Length="0.000000" Avg_Transaction_Waiting_Time="9223372036854775808" Max_Transaction_Waiting_Time="0"/>
			<SSDDevice.TSU.GC_Write_TR_Queue Name="GC_Write_TR_Queue@2@2" No_Of_Transactions_Enqueued="0" No_Of_Transactions_Dequeued="0" Avg_Queue_Length="0.000000" Max_Queue_Length="0" STDev_Queue_Length="0.000000" Avg_Transaction_Waiting_Time="9223372036854775808" Max_Transaction_Waiting_Time="0"/>
			<SSDDevice.TSU.GC_Write_TR_Queue Name="GC_Write_TR_Queue@2@3" No_Of_Transactions_Enqueued="0" No_Of_Transactions_Dequeued="0" Avg_Queue_Length="0.000000" Max_Queue_Length="0" STDev_Queue_Length="0.000000" Avg_Transaction_Waiting_Time="9223372036854775808" Max_Transaction_Waiting_Time="0"/>
			<SSDDevice.TSU.GC_Write_TR_Queue Name="GC_Write_TR_Queue@3@0" No_Of_Transactions_Enqueued="0" No_Of_Transactions_Dequeued="0" Avg_Queue_Length="0.000000" Max_Queue_Length="0" STDev_Queue_Length="0.000000" Avg_Transaction_Waiting_Time="9223372036854775808" Max_Transaction_Waiting_Time="0"/>
			<SSDDevice.TSU.GC_Write_TR_Queue Name="GC_Write_TR_Queue@3@1" No_Of_Transactions_Enqueued="0" No_Of_Transactions_Dequeued="0" Avg_Queue_Length="0.000000" Max_Queue_Length="0" STDev_Queue_Length="0.000000" Avg_Transaction_Waiting_Time="9223372036854775808" Max_Transaction_Waiting_Time="0"/>
			<SSDDevice.TSU.GC_Write_TR_Queue Name="GC_Write_TR_Queue@3@2" No_Of_Transactions_Enqueued="0" No_Of_Transactions_Dequeued="0" Avg_Queue_Length="0.000000" Max_Queue_Length="0" STDev_Queue_Length="0.000000" Avg_Transaction_Waiting_Time="9223372036854775808" Max_Transaction_Waiting_Time="0"/>
			<SSDDevice.TSU.GC_Write_TR_Queue Name="GC_Write_TR_Queue@3@3" No_Of_Transactions_Enqueued="0" No_Of_Transactions_Dequeued="0" Avg_Queue_Length="0.000000" Max_Queue_Length="0" STDev_Queue_Length="0.000000" Avg_Transaction_Waiting_Time="9223372036854775808" Max_Transaction_Waiting_Time="0"/>
			<SSDDevice.TSU.GC_Erase_TR_Queue Name="GC_Erase_TR_Queue@0@0" No_Of_Transactions_Enqueued="0" No_Of_Transactions_Dequeued="0" Avg_Queue_Length="0.000000" Max_Queue_Length="0" STDev_Queue_Length="0.000000" Avg_Transaction_Waiting_Time="9223372036854775808" Max_Transaction_Waiting_Time="0"/>
			<SSDDevice.TSU.GC_Erase_TR_Queue Name="GC_Erase_TR_Queue@0@1" No_Of_Transactions_Enqueued="0" No_Of_Transactions_Dequeued="0" Avg_Queue_Length="0.000000" Max_Queue_Length="0" STDev_Queue_Length="0.000000" Avg_Transaction_Waiting_Time="9223372036854775808" Max_Transaction_Waiting_Time="0"/>
			<SSDDevice.TSU.GC_Erase_TR_Queue Name="GC_Erase_TR_Queue@0@2" No_Of_Transactions_Enqueued="0" No_Of_Transactions_Dequeued="0" Avg_Queue_Length="0.000000" Max_Queue_Length="0" STDev_Queue_Length="0.000000" Avg_Transaction_Waiting_Time="9223372036854775808" Max_Transaction_Waiting_Time="0"/>
			<SSDDevice.TSU.GC_Erase_TR_Queue Name="GC_Erase_TR_Queue@0@3" No_Of_Transactions_Enqueued="0" No_Of_Transactions_Dequeued="0" Avg_Queue_Length="0.000000" Max_Queue_Length="0" STDev_Queue_Length="0.000000" Avg_Transaction_Waiting_Time="9223372036854775808" Max_Transaction_Waiting_Time="0"/>
			<SSDDevice.TSU.GC_Erase_TR_Queue Name="GC_Erase_TR_Queue@1@0" No_Of_Transactions_Enqueued="0" No_Of_Transactions_Dequeued="0" Avg_Queue_Length="0.000000" Max_Queue_Length="0" STDev_Queue_Length="0.000000" Avg_Transaction_Waiting_Time="9223372036854775808" Max_Transaction_Waiting_Time="0"/>
			<SSDDevice.TSU.GC_Erase_TR_Queue Name="GC_Erase_TR_Queue@1@1" No_Of_Transactions_Enqueued="0" No_Of_Transactions_Dequeued="0" Avg_Queue_Length="0.000000" Max_Queue_Length="0" STDev_Queue_Length="0.000000" Avg_Transaction_Waiting_Time="9223372036854775808" Max_Transaction_Waiting_Time="0"/>
			<SSDDevice.TSU.GC_Erase_TR_Queue Name="GC_Erase_TR_Queue@1@2" No_Of_Transactions_Enqueued="0" No_Of_Transactions_Dequeued="0" Avg_Queue_Length="0.000000" Max_Queue_Length="0" STDev_Queue_Length="0.000000" Avg_Transaction_Waiting_Time="9223372036854775808" Max_Transaction_Waiting_Time="0"/>
			<SSDDevice.TSU.GC_Erase_TR_Queue Name="GC_Erase_TR_Queue@1@3" No_Of_Transactions_Enqueued="0" No_Of_Transactions_Dequeued="0" Avg_Queue_Length="0.000000" Max_Queue_Length="0" STDev_Queue_Length="0.000000" Avg_Transaction_Waiting_Time="9223372036854775808" Max_Transaction_Waiting_Time="0"/>
			<SSDDevice.TSU.GC_Erase_TR_Queue Name="GC_Erase_TR_Queue@2@0" No_Of_Transactions_Enqueued="0" No_Of_Transactions_Dequeued="0" Avg_Queue_Length="0.000000" Max_Queue_Length="0" STDev_Queue_Length="0.000000" Avg_Transaction_Waiting_Time="9223372036854775808" Max_Transaction_Waiting_Time="0"/>
			<SSDDevice.TSU.GC_Erase_TR_Queue Name="GC_Erase_TR_Queue@2@1" No_Of_Transactions_Enqueued="0" No_Of_Transactions_Dequeued="0" Avg_Queue_Length="0.000000" Max_Queue_Length="0" STDev_Queue_Length="0.000000" Avg_Transaction_Waiting_Time="9223372036854775808" Max_Transaction_Waiting_Time="0"/>
			<SSDDevice.TSU.GC_Erase_TR_Queue Name="GC_Erase_TR_Queue@2@2" No_Of_Transactions_Enqueued="0" No_Of_Transactions_Dequeued="0" Avg_Queue_Length="0.000000" Max_Queue_Length="0" STDev_Queue_Length="0.000000" Avg_Transaction_Waiting_Time="9223372036854775808" Max_Transaction_Waiting_Time="0"/>
			<SSDDevice.TSU.GC_Erase_TR_Queue Name="GC_Erase_TR_Queue@2@3" No_Of_Transactions_Enqueued="0" No_Of_Transactions_Dequeued="0" Avg_Queue_Length="0.000000" Max_Queue_Length="0" STDev_Queue_Length="0.000000" Avg_Transaction_Waiting_Time="9223372036854775808" Max_Transaction_Waiting_Time="0"/>
			<SSDDevice.TSU.GC_Erase_TR_Queue Name="GC_Erase_TR_Queue@3@0" No_Of_Transactions_Enqueued="0" No_Of_Transactions_Dequeued="0" Avg_Queue_Length="0.000000" Max_Queue_Length="0" STDev_Queue_Length="0.000000" Avg_Transaction_Waiting_Time="9223372036854775808" Max_Transaction_Waiting_Time="0"/>
			<SSDDevice.TSU.GC_Erase_TR_Queue Name="GC_Erase_TR_Queue@3@1" No_Of_Transactions_Enqueued="0" No_Of_Transactions_Dequeued="0" Avg_Queue_Length="0.000000" Max_Queue_Length="0" STDev_Queue_Length="0.000000" Avg_Transaction_Waiting_Time="9223372036854775808" Max_Transaction_Waiting_Time="0"/>
			<SSDDevice.TSU.GC_Erase_TR_Queue Name="GC_Erase_TR_Queue@3@2" No_Of_Transactions_Enqueued="0" No_Of_Transactions_Dequeued="0" Avg_Queue_Length="0.000000" Max_Queue_Length="0" STDev_Queue_Length="0.000000" Avg_Transaction_Waiting_Time="9223372036854775808" Max_Transaction_Waiting_Time="0"/>
			<SSDDevice.TSU.GC_Erase_TR_Queue Name="GC_Erase_TR_Queue@3@3" No_Of_Transactions_Enqueued="0" No_Of_Transactions_Dequeued="0" Avg_Queue_Length="0.000000" Max_Queue_Length="0" STDev_Queue_Length="0.000000" Avg_Transaction_Waiting_Time="9223372036854775808" Max_Transaction_Waiting_Time="0"/>
		</SSDDevice.TSU>
		<SSDDevice.FlashChips ID="@0@0" Fraction_of_Time_in_Execution="0.723613" Fraction_of_Time_in_DataXfer="0.008475" Fraction_of_Time_in_DataXfer_and_Execution="0.000000" Fraction_of_Time_Idle="0.991525"/>
		<SSDDevice.FlashChips ID="@0@1" Fraction_of_Time_in_Execution="0.723613" Fraction_of_Time_in_DataXfer="0.008475" Fraction_of_Time_in_DataXfer_and_Execution="0.000000" Fraction_of_Time_Idle="0.991525"/>
		<SSDDevice.FlashChips ID="@0@2" Fraction_of_Time_in_Execution="0.722989" Fraction_of_Time_in_DataXfer="0.008444" Fraction_of_Time_in_DataXfer_and_Execution="0.000000" Fraction_of_Time_Idle="0.991556"/>
		<SSDDevice.FlashChips ID="@0@3" Fraction_of_Time_in_Execution="0.713922" Fraction_of_Time_in_DataXfer="0.008436" Fraction_of_Time_in_DataXfer_and_Execution="0.000000" Fraction_of_Time_Idle="0.991564"/>
		<SSDDevice.FlashChips ID="@1@0" Fraction_of_Time_in_Execution="0.724859" Fraction_of_Time_in_DataXfer="0.008537" Fraction_of_Time_in_DataXfer_and_Execution="0.000000" Fraction_of_Time_Idle="0.991463"/>
		<SSDDevice.FlashChips ID="@1@1" Fraction_of_Time_in_Execution="0.725482" Fraction_of_Time_in_DataXfer="0.008568" Fraction_of_Time_in_DataXfer_and_Execution="0.000000" Fraction_of_Time_Idle="0.991432"/>
		<SSDDevice.FlashChips ID="@1@2" Fraction_of_Time_in_Execution="0.723613" Fraction_of_Time_in_DataXfer="0.008441" Fraction_of_Time_in_DataXfer_and_Execution="0.000000" Fraction_of_Time_Idle="0.991559"/>
		<SSDDevice.FlashChips ID="@1@3" Fraction_of_Time_in_Execution="0.716415" Fraction_of_Time_in_DataXfer="0.008560" Fraction_of_Time_in_DataXfer_and_Execution="0.000000" Fraction_of_Time_Idle="0.991440"/>
		<SSDDevice.FlashChips ID="@2@0" Fraction_of_Time_in_Execution="0.726729" Fraction_of_Time_in_DataXfer="0.008630" Fraction_of_Time_in_DataXfer_and_Execution="0.000000" Fraction_of_Time_Idle="0.991370"/>
		<SSDDevice.FlashChips ID="@2@1" Fraction_of_Time_in_Execution="0.724236" Fraction_of_Time_in_DataXfer="0.008506" Fraction_of_Time_in_DataXfer_and_Execution="0.000000" Fraction_of_Time_Idle="0.991494"/>
		<SSDDevice.FlashChips ID="@2@2" Fraction_of_Time_in_Execution="0.715792" Fraction_of_Time_in_DataXfer="0.008529" Fraction_of_Time_in_DataXfer_and_Execution="0.000000" Fraction_of_Time_Idle="0.991471"/>
		<SSDDevice.FlashChips ID="@2@3" Fraction_of_Time_in_Execution="0.726729" Fraction_of_Time_in_DataXfer="0.008619" Fraction_of_Time_in_DataXfer_and_Execution="0.000000" Fraction_of_Time_Idle="0.991381"/>
		<SSDDevice.FlashChips ID="@3@0" Fraction_of_Time_in_Execution="0.723613" Fraction_of_Time_in_DataXfer="0.008475" Fraction_of_Time_in_DataXfer_and_Execution="0.000000" Fraction_of_Time_Idle="0.991525"/>
		<SSDDevice.FlashChips ID="@3@1" Fraction_of_Time_in_Execution="0.724859" Fraction_of_Time_in_DataXfer="0.008537" Fraction_of_Time_in_DataXfer_and_Execution="0.000000" Fraction_of_Time_Idle="0.991463"/>
		<SSDDevice.FlashChips ID="@3@2" Fraction_of_Time_in_Execution="0.716415" Fraction_of_Time_in_DataXfer="0.008560" Fraction_of_Time_in_DataXfer_and_Execution="0.000000" Fraction_of_Time_Idle="0.991440"/>
		<SSDDevice.FlashChips ID="@3@3" Fraction_of_Time_in_Execution="0.724859" Fraction_of_Time_in_DataXfer="0.008537" Fraction_of_Time_in_DataXfer_and_Execution="0.000000" Fraction_of_Time_Idle="0.991463"/>
	</SSDDevice>
</MQSim_Results>
